Metadata-Version: 2.1
Name: qt-collapsible-section-pyside6
Version: 0.1.0
Summary: This is a simple collapsable section for PySide6
Home-page: https://github.com/eyalk11/qt-collapsible-section
Author: Michael A. Voelkel 
Author-email: michael.alexander.voelkel@gmail.com
License: LGPL
Platform: UNKNOWN
License-File: LICENSE
